baml_client/__init__.py
baml_client/async_client.py
baml_client/config.py
baml_client/globals.py
baml_client/inlinedbaml.py
baml_client/parser.py
baml_client/runtime.py
baml_client/stream_types.py
baml_client/sync_client.py
baml_client/tracing.py
baml_client/type_builder.py
baml_client/type_map.py
baml_client/types.py
vity/__init__.py
vity/cli.py
vity/config.py
vity/llm.py
vity/prompts.py
vity/sanitizor.py
vity/schema.py
vity-0.2.5.dist-info/METADATA
vity-0.2.5.dist-info/WHEEL
vity-0.2.5.dist-info/entry_points.txt
vity-0.2.5.dist-info/licenses/LICENSE
vity-0.2.5.dist-info/RECORD
