Metadata-Version: 2.4
Name: vity
Version: 0.2.5
Summary: AI-powered terminal assistant for generating shell commands
Project-URL: Homepage, https://github.com/kaleab-ayenew/vity
Project-URL: Repository, https://github.com/kaleab-ayenew/vity
Project-URL: Documentation, https://github.com/kaleab-ayenew/vity#readme
Project-URL: Issues, https://github.com/kaleab-ayenew/vity/issues
Author-email: Kaleab Ayenew <ai@enhance.care>
License: MIT
License-File: LICENSE
Keywords: ai,assistant,cli,shell,terminal
Classifier: Development Status :: 4 - Beta
Classifier: Environment :: Console
Classifier: Intended Audience :: Developers
Classifier: License :: OSI Approved :: MIT License
Classifier: Operating System :: MacOS
Classifier: Operating System :: POSIX :: Linux
Classifier: Programming Language :: Python :: 3
Classifier: Programming Language :: Python :: 3.9
Classifier: Programming Language :: Python :: 3.10
Classifier: Programming Language :: Python :: 3.11
Classifier: Programming Language :: Python :: 3.12
Classifier: Programming Language :: Python :: 3.13
Classifier: Topic :: Software Development :: Libraries :: Python Modules
Classifier: Topic :: System :: Shells
Classifier: Topic :: Utilities
Requires-Python: >=3.9
Requires-Dist: baml-py==0.201.0
Requires-Dist: click>=8.0.0
Requires-Dist: openai>=1.0.0
Requires-Dist: pydantic-settings>=2.10.1
Requires-Dist: pydantic>=2.11.7
Requires-Dist: rich>=13.0.0
Provides-Extra: dev
Requires-Dist: black>=23.0.0; extra == 'dev'
Requires-Dist: mypy>=1.0.0; extra == 'dev'
Requires-Dist: pytest>=7.0.0; extra == 'dev'
Requires-Dist: ruff>=0.1.3; extra == 'dev'
